open_python/__init__.py
open_python/__main__.py
open_python-1.1.1.dist-info/LICENSE
open_python-1.1.1.dist-info/METADATA
open_python-1.1.1.dist-info/WHEEL
open_python-1.1.1.dist-info/top_level.txt
open_python-1.1.1.dist-info/RECORD
