Metadata-Version: 2.1
Name: open-python
Version: 1.1.1
Summary: Cross platform wrapper for opening a file/URL with system default application
Home-page: https://github.com/panda2134/open-python
Author: skratchdot
License: MIT
Keywords: cross platform,xdg-open,open,start,desktop
Platform: UNKNOWN
Classifier: Environment :: X11 Applications
Classifier: Environment :: MacOS X
Classifier: Environment :: Win32 (MS Windows)
Classifier: License :: OSI Approved :: MIT License
Classifier: Programming Language :: Python :: 2
Classifier: Programming Language :: Python :: 3
Classifier: Operating System :: Microsoft :: Windows
Classifier: Operating System :: MacOS :: MacOS X
Classifier: Operating System :: POSIX
Classifier: Topic :: Desktop Environment
License-File: LICENSE
Requires-Dist: six
